setup.py
GitServerGlue.egg-info/PKG-INFO
GitServerGlue.egg-info/SOURCES.txt
GitServerGlue.egg-info/dependency_links.txt
GitServerGlue.egg-info/entry_points.txt
GitServerGlue.egg-info/requires.txt
GitServerGlue.egg-info/top_level.txt
GitServerGlue.egg-info/zip-safe
gitserverglue/__init__.py
gitserverglue/common.py
gitserverglue/git.py
gitserverglue/http.py
gitserverglue/ssh.py
gitserverglue/streamingweb.py
gitserverglue/wsgihelper.py