Metadata-Version: 1.1
Name: GitServerGlue
Version: 0.3
Summary: Twisted-based implementation of the network protocols supported by git (git://, ssh:// and http://)
Home-page: https://github.com/mensi/gitserverglue
Author: Manuel Stocker
Author-email: mensi@mensi.ch
License: GPL
Keywords: git ssh http
Platform: UNKNOWN
Obsoletes: TwistedGit
